idisplay/__init__.py
idisplay-0.1.2.dist-info/DESCRIPTION.rst
idisplay-0.1.2.dist-info/METADATA
idisplay-0.1.2.dist-info/RECORD
idisplay-0.1.2.dist-info/WHEEL
idisplay-0.1.2.dist-info/metadata.json
idisplay-0.1.2.dist-info/pbr.json
idisplay-0.1.2.dist-info/top_level.txt
