Metadata-Version: 2.0
Name: idisplay
Version: 0.1.2
Summary: IPython rich display magic functions
Home-page: https://github.com/lebedov/idisplay/
Author: Lev Givon
Author-email: lev@columbia.edu
License: BSD
Platform: UNKNOWN
Classifier: Development Status :: 3 - Alpha
Classifier: Environment :: Console
Classifier: Intended Audience :: Developers
Classifier: License :: OSI Approved :: BSD License
Classifier: Operating System :: OS Independent
Classifier: Programming Language :: Python
Classifier: Topic :: Software Development
Requires-Dist: ipython (>=1.0)
